alu/alu_v.v
//TOP MODULE
module alu_v(
    input [3:0] a,b,
    input [2:0] SL,
    output[7:0] out
  );

reg [7:0] an;
reg [3:0] q,r;

assign out = an; 

always@(*)  
case(SL)
   0 :  begin
          an = a + b;
          end
   1 :  begin
         an =  a - b;
         end
   2 : begin 
         an = a * b;  
        end  
   3 : begin
        q = a / b;
        r = a % b;
        an = {q,r};
        #4;
        q = 4'bxxxx;
        r = 4'bxxxx;
        end
   4 : begin 
         an = a | b;  
        end 
   5 : begin 
         an = a & b;  
        end  
   6 : begin 
         an = a ^ b;  
        end  
   7 : begin 
         an = a << b;
         #2.5;
         an = a >> b;
        end       
endcase

endmodule

alu/tb_alu.v
module tb_alu;
//Inputs
 reg[3:0] A,B;
 reg[2:0] ALU_Sel;

//Outputs
 wire[7:0] ALU_Out;
 // Verilog code for ALU
 integer i;
 alu_v test_unit(
            .a(A),.b(B),  // ALU 4-bit Inputs                 
            .SL(ALU_Sel),// ALU Selection
            .out(ALU_Out) // ALU 8-bit Output
     );

initial begin
  $dumpfile("waveform_alu.vcd");
  $dumpvars(0,tb_alu );
    // hold reset state for 5 ns.
      A = 4'hB;
      B = 4'h3;
      ALU_Sel = 2'b00;
      
      for (i=0;i<8;i=i+1)
      begin
        #5;
        ALU_Sel = ALU_Sel + 1'b1;
      end;
      
    end
endmodule

alu/waveform_alu.vcd
$date
	Sun Dec 24 21:06:02 2023
$end
$version
	Icarus Verilog
$end
$timescale
	1s
$end
$scope module tb_alu $end
$var wire 8 ! ALU_Out [7:0] $end
$var reg 4 " A [3:0] $end
$var reg 3 # ALU_Sel [2:0] $end
$var reg 4 $ B [3:0] $end
$var integer 32 % i [31:0] $end
$scope module test_unit $end
$var wire 3 & SL [2:0] $end
$var wire 4 ' a [3:0] $end
$var wire 4 ( b [3:0] $end
$var wire 8 ) out [7:0] $end
$var reg 8 * an [7:0] $end
$var reg 4 + q [3:0] $end
$var reg 4 , r [3:0] $end
$upscope $end
$upscope $end
$enddefinitions $end
#0
$dumpvars
bx ,
bx +
b1110 *
b1110 )
b11 (
b1011 '
b0 &
b0 %
b11 $
b0 #
b1011 "
b1110 !
$end
#5
b1000 !
b1000 )
b1000 *
b1 %
b1 #
b1 &
#10
b100001 !
b100001 )
b100001 *
b10 %
b10 #
b10 &
#15
b110010 !
b110010 )
b110010 *
b10 ,
b11 +
b11 %
b11 #
b11 &
#19
bx ,
bx +
#20
b1011 !
b1011 )
b1011 *
b100 %
b100 #
b100 &
#25
b11 !
b11 )
b11 *
b101 %
b101 #
b101 &
#30
b1000 !
b1000 )
b1000 *
b110 %
b110 #
b110 &
#35
b1011000 !
b1011000 )
b1011000 *
b111 %
b111 #
b111 &
#38
b1 !
b1 )
b1 *
#40
b1110 !
b1110 )
b1110 *
b1000 %
b0 #
b0 &
